lightly_train/__init__.py
lightly_train/_checkpoint.py
lightly_train/_cli.py
lightly_train/_distributed.py
lightly_train/_env.py
lightly_train/_float32_matmul_precision.py
lightly_train/_lightning_rank_zero.py
lightly_train/_logging.py
lightly_train/_plot.py
lightly_train/_scaling.py
lightly_train/_system.py
lightly_train/_task_checkpoint.py
lightly_train/_torch_testing.py
lightly_train/_train_task_state.py
lightly_train/errors.py
lightly_train/model_wrappers.py
lightly_train/py.typed
lightly_train/types.py
lightly_train/_callbacks/__init__.py
lightly_train/_callbacks/callback_args.py
lightly_train/_callbacks/callback_helpers.py
lightly_train/_callbacks/checkpoint.py
lightly_train/_callbacks/export.py
lightly_train/_callbacks/learning_rate_monitor.py
lightly_train/_callbacks/mlflow_logging.py
lightly_train/_callbacks/tqdm_progress_bar.py
lightly_train/_commands/__init__.py
lightly_train/_commands/_warnings.py
lightly_train/_commands/common_helpers.py
lightly_train/_commands/embed.py
lightly_train/_commands/export.py
lightly_train/_commands/export_task.py
lightly_train/_commands/extract_video_frames.py
lightly_train/_commands/predict_task.py
lightly_train/_commands/predict_task_helpers.py
lightly_train/_commands/train.py
lightly_train/_commands/train_helpers.py
lightly_train/_commands/train_task.py
lightly_train/_commands/train_task_helpers.py
lightly_train/_configs/__init__.py
lightly_train/_configs/config.py
lightly_train/_configs/omegaconf_utils.py
lightly_train/_configs/validate.py
lightly_train/_data/__init__.py
lightly_train/_data/cache.py
lightly_train/_data/download.py
lightly_train/_data/file_helpers.py
lightly_train/_data/image_dataset.py
lightly_train/_data/infinite_cycle_iterator.py
lightly_train/_data/label_helpers.py
lightly_train/_data/mask_panoptic_segmentation_dataset.py
lightly_train/_data/mask_semantic_segmentation_dataset.py
lightly_train/_data/task_batch_collation.py
lightly_train/_data/task_data_args.py
lightly_train/_data/task_dataset.py
lightly_train-0.14.0.dist-info/licenses/LICENSE
lightly_train-0.14.0.dist-info/licenses/NOTICE
lightly_train-0.14.0.dist-info/METADATA
lightly_train-0.14.0.dist-info/WHEEL
lightly_train-0.14.0.dist-info/entry_points.txt
lightly_train-0.14.0.dist-info/top_level.txt
lightly_train-0.14.0.dist-info/RECORD
