Metadata-Version: 2.4
Name: lightly_train
Version: 0.14.0
Summary: Train models with self-supervised learning in a single command
Author: Lightly Team
License: AGPL-3.0
Keywords: machine-learning,computer-vision,deep-learning,self-supervised-learning,contrastive-learning,pytorch,python,pretrained-models,embeddings
Requires-Python: <3.13,>=3.8
License-File: LICENSE
License-File: NOTICE
Requires-Dist: albumentations!=1.4.16,!=1.4.17,!=1.4.18,!=1.4.19,!=1.4.20,!=1.4.21,!=1.4.22,!=1.4.23,!=1.4.5,!=1.4.9,>=1.3.1
Requires-Dist: eval-type-backport>=0.2
Requires-Dist: filelock>=3.0.0
Requires-Dist: fsspec>=2023.1.0
Requires-Dist: lightly>=1.5.20
Requires-Dist: omegaconf>=2.3
Requires-Dist: psutil>=5.0
Requires-Dist: pyarrow>=15.0.0
Requires-Dist: pytorch_lightning>=2.1
Requires-Dist: tensorboard>=2.10.0
Requires-Dist: torch>=2.1.0
Requires-Dist: torchmetrics[detection]>=0.8
Requires-Dist: torchvision>=0.16.0
Requires-Dist: transformers>=4.46
Requires-Dist: tqdm>=4.0.0
Provides-Extra: dev
Requires-Dist: licenseheaders>=0.8.8; extra == "dev"
Requires-Dist: mdformat>=0.7.21; python_version >= "3.9" and extra == "dev"
Requires-Dist: mdformat-myst>=0.3.0; python_version >= "3.9" and extra == "dev"
Requires-Dist: mypy>=1.10.0; extra == "dev"
Requires-Dist: pillow<12.0.0,>=10.3.0; extra == "dev"
Requires-Dist: pre-commit>=3.5.0; extra == "dev"
Requires-Dist: pytest-examples<0.0.16,>=0.0.13; extra == "dev"
Requires-Dist: pytest-mock>=3.14.0; extra == "dev"
Requires-Dist: pytest>=8.0.0; extra == "dev"
Requires-Dist: ruff>=0.4.0; extra == "dev"
Requires-Dist: types-PyYAML>=6.0.12; extra == "dev"
Requires-Dist: types-tqdm>=4.0.0; extra == "dev"
Requires-Dist: furo>=2024.04.27; extra == "dev"
Requires-Dist: myst_parser>=3.0; extra == "dev"
Requires-Dist: sphinx-autoapi>=3.0; extra == "dev"
Requires-Dist: sphinx-copybutton>=0.5.2; extra == "dev"
Requires-Dist: sphinx-design>=0.6.1; python_version >= "3.9" and extra == "dev"
Requires-Dist: sphinx-inline-tabs>=2023.4.21; extra == "dev"
Requires-Dist: sphinxcontrib-googleanalytics>=0.4; extra == "dev"
Requires-Dist: sphinx>=7.1; extra == "dev"
Provides-Extra: dicom
Requires-Dist: pydicom>=2.1.0; extra == "dicom"
Provides-Extra: mlflow
Requires-Dist: mlflow>=2.0.0; extra == "mlflow"
Provides-Extra: notebook
Requires-Dist: notebook>=7.2.3; extra == "notebook"
Provides-Extra: rfdetr
Requires-Dist: rfdetr>=1.3.0; extra == "rfdetr"
Requires-Dist: onnxruntime>=1.21.0; extra == "rfdetr"
Provides-Extra: super-gradients
Requires-Dist: super-gradients>=3.7; extra == "super-gradients"
Provides-Extra: tensorboard
Provides-Extra: timm
Requires-Dist: timm>=1.0.3; extra == "timm"
Provides-Extra: ultralytics
Requires-Dist: ultralytics>=8.1.0; extra == "ultralytics"
Provides-Extra: wandb
Requires-Dist: wandb>=0.17.2; extra == "wandb"
Provides-Extra: xformers
Requires-Dist: xformers>=0.0.18; extra == "xformers"
Provides-Extra: onnx
Requires-Dist: onnx>=1.15.0; extra == "onnx"
Provides-Extra: onnxruntime
Requires-Dist: onnxruntime>=1.21.0; extra == "onnxruntime"
Provides-Extra: onnxslim
Requires-Dist: onnxslim>=0.1.67; extra == "onnxslim"
Dynamic: license-file
